aemet/__init__.py
aemet/constants.py
aemet/models.py
aemet/utils.py
aemet/data/cod_ccaa.csv
aemet/data/cod_ccaa.json
aemet/data/cod_costas.csv
aemet/data/cod_costas.json
aemet/data/cods_idema.json
aemet/data/estaciones_contaminacion.csv
aemet/data/estaciones_contaminacion.json
aemet/data/municipios.csv
aemet/data/municipios.json
python_aemet-0.4.1.data/data/aemet/data/cod_ccaa.csv
python_aemet-0.4.1.data/data/aemet/data/cod_ccaa.json
python_aemet-0.4.1.data/data/aemet/data/cod_costas.csv
python_aemet-0.4.1.data/data/aemet/data/cod_costas.json
python_aemet-0.4.1.data/data/aemet/data/cods_idema.json
python_aemet-0.4.1.data/data/aemet/data/estaciones_contaminacion.csv
python_aemet-0.4.1.data/data/aemet/data/estaciones_contaminacion.json
python_aemet-0.4.1.data/data/aemet/data/municipios.csv
python_aemet-0.4.1.data/data/aemet/data/municipios.json
python_aemet-0.4.1.dist-info/LICENSE
python_aemet-0.4.1.dist-info/METADATA
python_aemet-0.4.1.dist-info/WHEEL
python_aemet-0.4.1.dist-info/entry_points.txt
python_aemet-0.4.1.dist-info/top_level.txt
python_aemet-0.4.1.dist-info/RECORD
