Metadata-Version: 2.1
Name: python-aemet
Version: 0.4.1
Summary: Cliente de la API de datos de AEMET
Home-page: https://github.com/pablo-moreno/python-aemet
Author: Pablo Moreno
Author-email: pablomoreno.inf@gmail.com
License: MIT
Keywords: aemet weather api spain opendata
Classifier: Development Status :: 5 - Production/Stable
Classifier: Intended Audience :: Developers
Classifier: Topic :: Software Development :: Build Tools
Classifier: License :: OSI Approved :: MIT License
Classifier: Operating System :: OS Independent
Classifier: Programming Language :: Python :: 3.6
Classifier: Programming Language :: Python :: 3.7
License-File: LICENSE
Requires-Dist: urllib3
Requires-Dist: requests
Requires-Dist: click
Provides-Extra: dev
Requires-Dist: check-manifest ; extra == 'dev'
Provides-Extra: test
Requires-Dist: coverage ; extra == 'test'
